{
  "coordinates": [
    {
      "lat": 45.43363809203729,
      "lng": 12.334960907080212
    },
    {
      "lat": 45.43341222762281,
      "lng": 12.33504137335066
    },
    {
      "lat": 45.43344987175467,
      "lng": 12.33528813658003
    },
    {
      "lat": 45.43338964113165,
      "lng": 12.335411518194714
    },
    {
      "lat": 45.43331811718333,
      "lng": 12.335470526793042
    },
    {
      "lat": 45.43307342930616,
      "lng": 12.33551880655531
    },
    {
      "lat": 45.43284003372709,
      "lng": 12.33554026422743
    },
    {
      "lat": 45.43201561258453,
      "lng": 12.335942595579663
    },
    {
      "lat": 45.43182738689073,
      "lng": 12.334987729170361
    },
    {
      "lat": 45.431657983229584,
      "lng": 12.333630531408826
    },
    {
      "lat": 45.433058371556015,
      "lng": 12.333458870031873
    },
    {
      "lat": 45.43321647773241,
      "lng": 12.333866565802136
    },
    {
      "lat": 45.433487515861415,
      "lng": 12.334494202711621
    }
  ],
  "centroid": {
    "lat": 45.432952673893666,
    "lng": 12.33489323288353
  },
  "historicalName": "Calle Larga de San Moisè",
  "englishName": "Long Street of Saint Moses",
  "historicalDescription": "This street was located in the San Marco sestiere, known for its proximity to the Church of San Moisè and the bustling commercial activity in the area during the 15th century.",
  "nameConfidence": "medium",
  "areaInSquareMeters": 29376.11,
  "center": {
    "lat": 45.43254769811212,
    "lng": 12.334566909912711
  }
}